generic_grader/__init__.py
generic_grader/class_/class_attributes_match_reference.py
generic_grader/class_/class_is_defined.py
generic_grader/class_/class_method_signatures_match_reference.py
generic_grader/class_/instance_attributes_match_reference.py
generic_grader/file/file_closed.py
generic_grader/file/file_has_n_lines.py
generic_grader/file/file_is_identical.py
generic_grader/file/file_lines_are_random.py
generic_grader/file/file_lines_match_reference.py
generic_grader/file/file_lines_span_range.py
generic_grader/file/file_presence.py
generic_grader/function/function_not_defined.py
generic_grader/function/function_random_return_length.py
generic_grader/function/function_return_values_match_reference.py
generic_grader/function/random_function_calls.py
generic_grader/function/static_loop_depth.py
generic_grader/image/ocr_words_match_reference.py
generic_grader/image/pixel_overlap.py
generic_grader/image/plot_prop_matches_reference.py
generic_grader/output/output_lines_are_random.py
generic_grader/output/output_lines_match_reference.py
generic_grader/output/output_values_match_reference.py
generic_grader/random/random_func_return_range.py
generic_grader/style/comments.py
generic_grader/style/docstring.py
generic_grader/style/program_length.py
generic_grader/utils/array_diff.py
generic_grader/utils/decorators.py
generic_grader/utils/docs.py
generic_grader/utils/exceptions.py
generic_grader/utils/file_set_up.py
generic_grader/utils/importer.py
generic_grader/utils/math_utils.py
generic_grader/utils/mocks.py
generic_grader/utils/options.py
generic_grader/utils/patches.py
generic_grader/utils/plot.py
generic_grader/utils/reference_test.py
generic_grader/utils/resource_limits.py
generic_grader/utils/static.py
generic_grader/utils/turtle_canvas.py
generic_grader/utils/user.py
generic_grader-0.1.24.dist-info/METADATA
generic_grader-0.1.24.dist-info/WHEEL
generic_grader-0.1.24.dist-info/licenses/LICENSE
generic_grader-0.1.24.dist-info/RECORD
