Metadata-Version: 2.4
Name: generic-grader
Version: 0.1.24
Summary: A collection of parameterizable tests for automatic grading.
Project-URL: Homepage, https://github.com/Purdue-EBEC/generic-grader
Project-URL: Bug Tracker, https://github.com/Purdue-EBEC/generic-grader/issues
Author-email: John Cole <jhcole@purdue.edu>, Jack Scarfo <jscarfo@purdue.edu>, Advait Jawaji <ajawaji@purdue.edu>
License-File: LICENSE
Classifier: License :: OSI Approved :: GNU General Public License v3 (GPLv3)
Classifier: Operating System :: OS Independent
Classifier: Programming Language :: Python :: 3
Requires-Python: >=3.11
Requires-Dist: attrs==25.4.0
Requires-Dist: freezegun==1.5.5
Requires-Dist: gradescope-utils<1,>=0.5.0
Requires-Dist: matplotlib<4,>=3.7.0
Requires-Dist: numpy<3,>=2.0.0
Requires-Dist: parameterized<1,>=0.8.1
Requires-Dist: pillow<12,>=9.4.0
Requires-Dist: pytesseract<1,>=0.3.13
Requires-Dist: python-dateutil<3,>=2.8.2
Requires-Dist: pytz==2025.2
Requires-Dist: rapidfuzz<4,>=3.1.1
Requires-Dist: scipy<2,>=1.10.1
Provides-Extra: dev
Requires-Dist: build; extra == 'dev'
Requires-Dist: coverage; extra == 'dev'
Requires-Dist: pre-commit<5,>=3; extra == 'dev'
Requires-Dist: pytest; extra == 'dev'
Requires-Dist: pytest-cov; extra == 'dev'
Requires-Dist: twine; extra == 'dev'
